LICENSE
MANIFEST.in
README.md
setup.cfg
setup.py
watchme/__init__.py
watchme/defaults.py
watchme/version.py
watchme.egg-info/PKG-INFO
watchme.egg-info/SOURCES.txt
watchme.egg-info/dependency_links.txt
watchme.egg-info/entry_points.txt
watchme.egg-info/not-zip-safe
watchme.egg-info/requires.txt
watchme.egg-info/top_level.txt
watchme/client/__init__.py
watchme/client/activate.py
watchme/client/add.py
watchme/client/create.py
watchme/client/deactivate.py
watchme/client/edit.py
watchme/client/export.py
watchme/client/get.py
watchme/client/init.py
watchme/client/inspect.py
watchme/client/ls.py
watchme/client/monitor.py
watchme/client/protect.py
watchme/client/remove.py
watchme/client/run.py
watchme/client/schedule.py
watchme/command/__init__.py
watchme/command/commit.py
watchme/command/create.py
watchme/command/utils.py
watchme/config/__init__.py
watchme/config/watchme.cfg
watchme/logger/__init__.py
watchme/logger/message.py
watchme/logger/namer.py
watchme/logger/progress.py
watchme/logger/spinner.py
watchme/tasks/__init__.py
watchme/tasks/decorators.py
watchme/tasks/worker.py
watchme/tests/__init__.py
watchme/tests/helpers.sh
watchme/tests/test_client.py
watchme/tests/test_client.sh
watchme/tests/test_decorators.py
watchme/tests/test_psutils_decorator.py
watchme/tests/test_utils.py
watchme/tests/test_utils.sh
watchme/tests/test_watchers.sh
watchme/utils/__init__.py
watchme/utils/fileio.py
watchme/utils/terminal.py
watchme/watchers/README.md
watchme/watchers/__init__.py
watchme/watchers/data.py
watchme/watchers/schedule.py
watchme/watchers/settings.py
watchme/watchers/gpu/README.md
watchme/watchers/gpu/__init__.py
watchme/watchers/gpu/decorators.py
watchme/watchers/gpu/pynvml.py
watchme/watchers/gpu/tasks.py
watchme/watchers/psutils/README.md
watchme/watchers/psutils/__init__.py
watchme/watchers/psutils/decorators.py
watchme/watchers/psutils/tasks.py
watchme/watchers/results/__init__.py
watchme/watchers/results/tasks.py
watchme/watchers/urls/__init__.py
watchme/watchers/urls/helpers.py
watchme/watchers/urls/tasks.py