Metadata-Version: 2.1
Name: watchme
Version: 0.0.29
Summary: reproducible monitoring client with exporters
Home-page: http://www.github.com/vsoch/watchme
Author: Vanessa Sochat
Author-email: vsochat@stanford.edu
Maintainer: Vanessa Sochat
Maintainer-email: vsochat@stanford.edu
License: LICENSE
Keywords: web,changes,cron,reproducible,version-control
Platform: UNKNOWN
Classifier: Intended Audience :: Science/Research
Classifier: Intended Audience :: Developers
Classifier: Programming Language :: Python
Classifier: Topic :: Software Development
Classifier: Topic :: Scientific/Engineering
Classifier: Operating System :: Unix
Classifier: Programming Language :: Python :: 2.7
Classifier: Programming Language :: Python :: 3
Provides-Extra: all
Provides-Extra: watchers
Provides-Extra: watcher-urls-dynamic
Provides-Extra: watcher-psutils
License-File: LICENSE
